{
    "version": "1.23.7",
    "architecture": {
        "32bit": {
            "url": "https://github.com/stripe/stripe-cli/releases/download/v1.23.7/stripe_1.23.7_windows_i386.zip",
            "bin": [
                "stripe.exe"
            ],
            "hash": "c48dceb6244c1b0eb48299efb15eb12c631d4469f46ba21764c9095b438d9ba7"
        },
        "64bit": {
            "url": "https://github.com/stripe/stripe-cli/releases/download/v1.23.7/stripe_1.23.7_windows_x86_64.zip",
            "bin": [
                "stripe.exe"
            ],
            "hash": "1d6851d23f4fb8298c6aa29a861e26535d09ae394932da581ae3e9a4e235c434"
        }
    },
    "homepage": "https://stripe.com",
    "license": "Apache 2.0",
    "description": "Stripe CLI utility"
}