{
    "version": "1.7.5",
    "architecture": {
        "32bit": {
            "url": "https://github.com/stripe/stripe-cli/releases/download/v1.7.5/stripe_1.7.5_windows_i386.zip",
            "bin": [
                "stripe.exe"
            ],
            "hash": "9d4d2b209a9d7a556df8089bdd54aac5c81b647917f44fe5366219dc75491229"
        },
        "64bit": {
            "url": "https://github.com/stripe/stripe-cli/releases/download/v1.7.5/stripe_1.7.5_windows_x86_64.zip",
            "bin": [
                "stripe.exe"
            ],
            "hash": "53aef939268dbdf8bb8406d07be30988a9bf4cd8460cf20c548769f990e05316"
        }
    },
    "homepage": "https://stripe.com",
    "license": "Apache 2.0",
    "description": "Stripe CLI utility"
}